[
    {
        "name": "Autos",
        "description": "Los mejores precios en autos o kilometro, de alta y media gama.",
        "cost": 13500,
        "currency": "USD",
        "imgSrc": "img/cat1.jpg",
        "soldCount": 122
    },
    {
        "name": "Juguetes",
        "description": "Encuentra aquí los mejores precios para niños/as de cualquier edad.",
        "cost": 14500,
        "currency": "USD",
        "imgSrc": "img/cat2.jpg",
        "soldCount": 354
    },
    {
        "name": "Muebles",
        "description": "Muebles antiguos, nuevos y para ser armados por uno mismo.",
        "cost": 12500,
        "currency": "USD",
        "imgSrc": "img/cat3.jpg",
        "soldCount": 157
    },
    {
        "name": "Herramientas",
        "description": "Herramientas para cualquier tipo de trabajo.",
        "cost": 15200,
        "currency": "USD",
        "imgSrc": "img/cat4.jpg",
        "soldCount": 452
    }
]
